setup.py
microfilters/__init__.py
microfilters/filters.py
microfilters.egg-info/PKG-INFO
microfilters.egg-info/SOURCES.txt
microfilters.egg-info/dependency_links.txt
microfilters.egg-info/top_level.txt
microfilters/runtests/__init__.py
microfilters/runtests/runtests.py
microfilters/tests/__init__.py
microfilters/tests/filters.py
microfilters/tests/tests.py