Metadata-Version: 1.0
Name: microfilters
Version: 0.1
Summary: Minimalist skeleton classes to build filters in Python.
Home-page: https://github.com/lukasbuenger/microfilters
Author: Lukas Buenger
Author-email: lukasbuenger@gmail.com
License: BSD
Download-URL: http://pypi.python.org/pypi/microfilters/
Platform: UNKNOWN
Classifier: Development Status :: 5 - Production/Stable
Classifier: Environment :: Web Environment
Classifier: Intended Audience :: Developers
Classifier: License :: OSI Approved :: BSD License
Classifier: Operating System :: OS Independent
Classifier: Programming Language :: Python
Classifier: Programming Language :: Python :: 3
Classifier: Topic :: Internet :: WWW/HTTP
